{
  "TR - Open home page-8" : {
    "transaction" : "TR - Open home page-8",
    "sampleCount" : 120,
    "errorCount" : 0,
    "errorPct" : 0.0,
    "meanResTime" : 573.1333333333332,
    "medianResTime" : 517.5,
    "minResTime" : 390.0,
    "maxResTime" : 2038.0,
    "pct1ResTime" : 717.7,
    "pct2ResTime" : 909.5999999999999,
    "pct3ResTime" : 1944.7599999999966,
    "throughput" : 0.3358371861321631,
    "receivedKBytesPerSec" : 3.7543252156354603,
    "sentKBytesPerSec" : 0.3539026467468572
  },
  "TR - Open home page-7" : {
    "transaction" : "TR - Open home page-7",
    "sampleCount" : 120,
    "errorCount" : 0,
    "errorPct" : 0.0,
    "meanResTime" : 424.84999999999997,
    "medianResTime" : 391.5,
    "minResTime" : 329.0,
    "maxResTime" : 859.0,
    "pct1ResTime" : 574.6000000000001,
    "pct2ResTime" : 636.3499999999997,
    "pct3ResTime" : 853.3299999999998,
    "throughput" : 0.3362889394567813,
    "receivedKBytesPerSec" : 2.0095946124410093,
    "sentKBytesPerSec" : 0.3464695616473674
  },
  "TR - Open home page-6" : {
    "transaction" : "TR - Open home page-6",
    "sampleCount" : 120,
    "errorCount" : 0,
    "errorPct" : 0.0,
    "meanResTime" : 613.5000000000002,
    "medianResTime" : 548.5,
    "minResTime" : 422.0,
    "maxResTime" : 1441.0,
    "pct1ResTime" : 838.9000000000001,
    "pct2ResTime" : 1083.8999999999992,
    "pct3ResTime" : 1439.32,
    "throughput" : 0.3362333459420838,
    "receivedKBytesPerSec" : 3.2532026445102904,
    "sentKBytesPerSec" : 0.3553708461172054
  },
  "TR - Open home page-5" : {
    "transaction" : "TR - Open home page-5",
    "sampleCount" : 120,
    "errorCount" : 0,
    "errorPct" : 0.0,
    "meanResTime" : 450.9583333333332,
    "medianResTime" : 420.5,
    "minResTime" : 333.0,
    "maxResTime" : 1083.0,
    "pct1ResTime" : 572.7000000000003,
    "pct2ResTime" : 708.5999999999999,
    "pct3ResTime" : 1046.6699999999987,
    "throughput" : 0.33681279664085373,
    "receivedKBytesPerSec" : 3.300425524375423,
    "sentKBytesPerSec" : 0.34711891737140066
  },
  "TR - Open home page-4" : {
    "transaction" : "TR - Open home page-4",
    "sampleCount" : 120,
    "errorCount" : 0,
    "errorPct" : 0.0,
    "meanResTime" : 453.87500000000017,
    "medianResTime" : 415.0,
    "minResTime" : 342.0,
    "maxResTime" : 1090.0,
    "pct1ResTime" : 585.0,
    "pct2ResTime" : 674.8499999999999,
    "pct3ResTime" : 1028.6799999999976,
    "throughput" : 0.3366842771248285,
    "receivedKBytesPerSec" : 3.146017011849884,
    "sentKBytesPerSec" : 0.3467563100244938
  },
  "TR - Open home page-3" : {
    "transaction" : "TR - Open home page-3",
    "sampleCount" : 120,
    "errorCount" : 0,
    "errorPct" : 0.0,
    "meanResTime" : 448.2500000000001,
    "medianResTime" : 419.5,
    "minResTime" : 335.0,
    "maxResTime" : 728.0,
    "pct1ResTime" : 573.8000000000002,
    "pct2ResTime" : 656.7499999999998,
    "pct3ResTime" : 727.16,
    "throughput" : 0.33659644890746404,
    "receivedKBytesPerSec" : 3.145021024129758,
    "sentKBytesPerSec" : 0.3468192512131497
  },
  "TR - Open home page-2" : {
    "transaction" : "TR - Open home page-2",
    "sampleCount" : 120,
    "errorCount" : 0,
    "errorPct" : 0.0,
    "meanResTime" : 283.9666666666665,
    "medianResTime" : 279.0,
    "minResTime" : 232.0,
    "maxResTime" : 662.0,
    "pct1ResTime" : 310.0,
    "pct2ResTime" : 332.84999999999997,
    "pct3ResTime" : 602.9899999999977,
    "throughput" : 0.3366852217633327,
    "receivedKBytesPerSec" : 0.7830095967563184,
    "sentKBytesPerSec" : 0.3434748212061187
  },
  "TR - Open home page-1" : {
    "transaction" : "TR - Open home page-1",
    "sampleCount" : 119,
    "errorCount" : 0,
    "errorPct" : 0.0,
    "meanResTime" : 1074.9831932773109,
    "medianResTime" : 1031.0,
    "minResTime" : 670.0,
    "maxResTime" : 1724.0,
    "pct1ResTime" : 1439.0,
    "pct2ResTime" : 1632.0,
    "pct3ResTime" : 1721.6,
    "throughput" : 0.3353047751344741,
    "receivedKBytesPerSec" : 6.024911370530091,
    "sentKBytesPerSec" : 0.23739840036376342
  },
  "TR - Login-8" : {
    "transaction" : "TR - Login-8",
    "sampleCount" : 120,
    "errorCount" : 0,
    "errorPct" : 0.0,
    "meanResTime" : 448.6249999999999,
    "medianResTime" : 419.5,
    "minResTime" : 332.0,
    "maxResTime" : 856.0,
    "pct1ResTime" : 612.9000000000002,
    "pct2ResTime" : 684.75,
    "pct3ResTime" : 831.2199999999991,
    "throughput" : 0.3295155297923228,
    "receivedKBytesPerSec" : 3.129861212177796,
    "sentKBytesPerSec" : 0.4232322349940001
  },
  "TR - Login-7" : {
    "transaction" : "TR - Login-7",
    "sampleCount" : 120,
    "errorCount" : 0,
    "errorPct" : 0.0,
    "meanResTime" : 467.02500000000003,
    "medianResTime" : 429.5,
    "minResTime" : 343.0,
    "maxResTime" : 1197.0,
    "pct1ResTime" : 582.9,
    "pct2ResTime" : 693.1499999999996,
    "pct3ResTime" : 1130.0099999999975,
    "throughput" : 0.32740100894077584,
    "receivedKBytesPerSec" : 3.1092624772183464,
    "sentKBytesPerSec" : 0.4207774392739337
  },
  "TR - Login-6" : {
    "transaction" : "TR - Login-6",
    "sampleCount" : 120,
    "errorCount" : 0,
    "errorPct" : 0.0,
    "meanResTime" : 291.02500000000026,
    "medianResTime" : 280.0,
    "minResTime" : 235.0,
    "maxResTime" : 634.0,
    "pct1ResTime" : 342.30000000000007,
    "pct2ResTime" : 422.7499999999997,
    "pct3ResTime" : 609.8499999999991,
    "throughput" : 0.329017717604093,
    "receivedKBytesPerSec" : 0.8159789339551768,
    "sentKBytesPerSec" : 0.41918699379253244
  },
  "TR - Search product" : {
    "transaction" : "TR - Search product",
    "sampleCount" : 120,
    "errorCount" : 0,
    "errorPct" : 0.0,
    "meanResTime" : 3528.1750000000006,
    "medianResTime" : 3492.5,
    "minResTime" : 2418.0,
    "maxResTime" : 4747.0,
    "pct1ResTime" : 4182.3,
    "pct2ResTime" : 4394.099999999999,
    "pct3ResTime" : 4718.019999999999,
    "throughput" : 0.32771752933754633,
    "receivedKBytesPerSec" : 20.782211923490248,
    "sentKBytesPerSec" : 2.205276542388897
  },
  "TR - Login-4" : {
    "transaction" : "TR - Login-4",
    "sampleCount" : 120,
    "errorCount" : 120,
    "errorPct" : 100.0,
    "meanResTime" : 1054.0833333333328,
    "medianResTime" : 1019.0,
    "minResTime" : 699.0,
    "maxResTime" : 1785.0,
    "pct1ResTime" : 1343.0,
    "pct2ResTime" : 1439.6,
    "pct3ResTime" : 1755.8099999999988,
    "throughput" : 0.3300039600475206,
    "receivedKBytesPerSec" : 5.040192806532429,
    "sentKBytesPerSec" : 0.5331465344771638
  },
  "TR - Login-3" : {
    "transaction" : "TR - Login-3",
    "sampleCount" : 120,
    "errorCount" : 0,
    "errorPct" : 0.0,
    "meanResTime" : 1027.8583333333338,
    "medianResTime" : 994.5,
    "minResTime" : 637.0,
    "maxResTime" : 1765.0,
    "pct1ResTime" : 1361.6000000000001,
    "pct2ResTime" : 1528.5,
    "pct3ResTime" : 1737.2799999999988,
    "throughput" : 0.3319309251744712,
    "receivedKBytesPerSec" : 7.891106688823055,
    "sentKBytesPerSec" : 0.38127755718201706
  },
  "TR - Login user" : {
    "transaction" : "TR - Login user",
    "sampleCount" : 120,
    "errorCount" : 120,
    "errorPct" : 100.0,
    "meanResTime" : 5112.1,
    "medianResTime" : 5094.0,
    "minResTime" : 4091.0,
    "maxResTime" : 6203.0,
    "pct1ResTime" : 5831.7,
    "pct2ResTime" : 5949.45,
    "pct3ResTime" : 6197.54,
    "throughput" : 0.3316355435921104,
    "receivedKBytesPerSec" : 33.01534393024046,
    "sentKBytesPerSec" : 2.918284829332058
  },
  "TR - Login-2" : {
    "transaction" : "TR - Login-2",
    "sampleCount" : 120,
    "errorCount" : 0,
    "errorPct" : 0.0,
    "meanResTime" : 776.4583333333331,
    "medianResTime" : 750.5,
    "minResTime" : 444.0,
    "maxResTime" : 1804.0,
    "pct1ResTime" : 1016.9,
    "pct2ResTime" : 1142.5499999999995,
    "pct3ResTime" : 1722.099999999997,
    "throughput" : 0.33440062867318193,
    "receivedKBytesPerSec" : 5.102349996063826,
    "sentKBytesPerSec" : 0.3835647054766463
  },
  "TR - Login-1" : {
    "transaction" : "TR - Login-1",
    "sampleCount" : 120,
    "errorCount" : 0,
    "errorPct" : 0.0,
    "meanResTime" : 1047.0250000000008,
    "medianResTime" : 964.0,
    "minResTime" : 629.0,
    "maxResTime" : 2054.0,
    "pct1ResTime" : 1483.9,
    "pct2ResTime" : 1552.5,
    "pct3ResTime" : 1980.2899999999972,
    "throughput" : 0.33501772802144114,
    "receivedKBytesPerSec" : 7.964446679834724,
    "sentKBytesPerSec" : 0.35000737213490046
  },
  "TR - Open home page" : {
    "transaction" : "TR - Open home page",
    "sampleCount" : 120,
    "errorCount" : 0,
    "errorPct" : 0.0,
    "meanResTime" : 4327.508333333334,
    "medianResTime" : 4219.0,
    "minResTime" : 3554.0,
    "maxResTime" : 5839.0,
    "pct1ResTime" : 4989.1,
    "pct2ResTime" : 5154.549999999999,
    "pct3ResTime" : 5813.589999999999,
    "throughput" : 0.33180885597836607,
    "receivedKBytesPerSec" : 25.088467780150363,
    "sentKBytesPerSec" : 2.6412125349781834
  },
  "Total" : {
    "transaction" : "Total",
    "sampleCount" : 2519,
    "errorCount" : 120,
    "errorPct" : 4.7637954,
    "meanResTime" : 617.1417229059158,
    "medianResTime" : 500.0,
    "minResTime" : 39.0,
    "maxResTime" : 2359.0,
    "pct1ResTime" : 1100.0,
    "pct2ResTime" : 1264.0,
    "pct3ResTime" : 1597.6000000000004,
    "throughput" : 6.1668551731566765,
    "receivedKBytesPerSec" : 70.04492157854601,
    "sentKBytesPerSec" : 6.898754667524739
  },
  "TR - Search product-3" : {
    "transaction" : "TR - Search product-3",
    "sampleCount" : 120,
    "errorCount" : 0,
    "errorPct" : 0.0,
    "meanResTime" : 983.4583333333335,
    "medianResTime" : 948.5,
    "minResTime" : 580.0,
    "maxResTime" : 1639.0,
    "pct1ResTime" : 1263.0,
    "pct2ResTime" : 1391.6499999999994,
    "pct3ResTime" : 1627.4499999999996,
    "throughput" : 0.32869598086989393,
    "receivedKBytesPerSec" : 7.184125730321382,
    "sentKBytesPerSec" : 0.38983428929081104
  },
  "TR - Search product-4" : {
    "transaction" : "TR - Search product-4",
    "sampleCount" : 120,
    "errorCount" : 0,
    "errorPct" : 0.0,
    "meanResTime" : 389.4583333333333,
    "medianResTime" : 360.0,
    "minResTime" : 286.0,
    "maxResTime" : 1185.0,
    "pct1ResTime" : 473.9,
    "pct2ResTime" : 558.95,
    "pct3ResTime" : 1094.9099999999967,
    "throughput" : 0.3308820488216463,
    "receivedKBytesPerSec" : 1.8841831616538038,
    "sentKBytesPerSec" : 0.4061867963586431
  },
  "TR - Search product-1" : {
    "transaction" : "TR - Search product-1",
    "sampleCount" : 120,
    "errorCount" : 0,
    "errorPct" : 0.0,
    "meanResTime" : 997.4583333333331,
    "medianResTime" : 932.5,
    "minResTime" : 584.0,
    "maxResTime" : 2359.0,
    "pct1ResTime" : 1325.8000000000002,
    "pct2ResTime" : 1490.3999999999996,
    "pct3ResTime" : 2242.8699999999953,
    "throughput" : 0.3311084683750024,
    "receivedKBytesPerSec" : 7.888282019568511,
    "sentKBytesPerSec" : 0.3874141532314807
  },
  "TR - Search product-2" : {
    "transaction" : "TR - Search product-2",
    "sampleCount" : 120,
    "errorCount" : 0,
    "errorPct" : 0.0,
    "meanResTime" : 808.3333333333334,
    "medianResTime" : 795.5,
    "minResTime" : 318.0,
    "maxResTime" : 2028.0,
    "pct1ResTime" : 1098.9,
    "pct2ResTime" : 1175.9499999999998,
    "pct3ResTime" : 1938.7499999999966,
    "throughput" : 0.32927050120458123,
    "receivedKBytesPerSec" : 2.4569345911009157,
    "sentKBytesPerSec" : 0.4183621810878
  },
  "TR - Search product-5" : {
    "transaction" : "TR - Search product-5",
    "sampleCount" : 120,
    "errorCount" : 0,
    "errorPct" : 0.0,
    "meanResTime" : 281.2333333333334,
    "medianResTime" : 276.5,
    "minResTime" : 231.0,
    "maxResTime" : 420.0,
    "pct1ResTime" : 321.30000000000007,
    "pct2ResTime" : 367.9999999999998,
    "pct3ResTime" : 418.53,
    "throughput" : 0.329330142490175,
    "receivedKBytesPerSec" : 0.8163705082456035,
    "sentKBytesPerSec" : 0.395898356025095
  },
  "TR - Search product-6" : {
    "transaction" : "TR - Search product-6",
    "sampleCount" : 120,
    "errorCount" : 0,
    "errorPct" : 0.0,
    "meanResTime" : 68.23333333333333,
    "medianResTime" : 46.0,
    "minResTime" : 39.0,
    "maxResTime" : 271.0,
    "pct1ResTime" : 163.0,
    "pct2ResTime" : 192.39999999999986,
    "pct3ResTime" : 268.8999999999999,
    "throughput" : 0.32945039437957624,
    "receivedKBytesPerSec" : 0.6917305420076707,
    "sentKBytesPerSec" : 0.22167121262453912
  }
}